{
  "auth": {
    "mrbackenddb0015c4": {
      "service": "Cognito",
      "providerPlugin": "awscloudformation",
      "dependsOn": [],
      "customAuth": false,
      "frontendAuthConfig": {
        "socialProviders": [],
        "usernameAttributes": [],
        "signupAttributes": [
          "EMAIL"
        ],
        "passwordProtectionSettings": {
          "passwordPolicyMinLength": 8,
          "passwordPolicyCharacters": []
        },
        "mfaConfiguration": "OFF",
        "mfaTypes": [
          "SMS"
        ],
        "verificationMechanisms": [
          "EMAIL"
        ]
      }
    }
  },
  "api": {
    "backendApi": {
      "service": "AppSync",
      "providerPlugin": "awscloudformation",
      "dependsOn": [
        {
          "category": "auth",
          "resourceName": "mrbackenddb0015c4",
          "attributes": [
            "UserPoolId"
          ]
        }
      ],
      "output": {
        "authConfig": {
          "defaultAuthentication": {
            "authenticationType": "AMAZON_COGNITO_USER_POOLS",
            "userPoolConfig": {
              "userPoolId": "authmrbackenddb0015c4"
            }
          },
          "additionalAuthenticationProviders": [
            {
              "authenticationType": "API_KEY",
              "apiKeyConfig": {
                "apiKeyExpirationDays": 7,
                "apiKeyExpirationDate": "2022-12-05T07:39:54.696Z",
                "description": ""
              }
            }
          ]
        }
      }
    }
  },
  "function": {
    "backendFunc": {
      "build": true,
      "providerPlugin": "awscloudformation",
      "service": "Lambda",
      "dependsOn": [
        {
          "category": "auth",
          "resourceName": "mrbackenddb0015c4",
          "attributes": [
            "UserPoolId"
          ]
        },
        {
          "category": "api",
          "resourceName": "backendApi",
          "attributes": [
            "GraphQLAPIIdOutput",
            "GraphQLAPIEndpointOutput",
            "GraphQLAPIKeyOutput"
          ]
        }
      ]
    }
  }
}